niceterminal-0.1.2.dist-info/METADATA
niceterminal-0.1.2.dist-info/WHEEL
niceterminal-0.1.2.dist-info/entry_points.txt
niceterminal-0.1.2.dist-info/licenses/LICENSE
niceterminal/__init__.py
niceterminal/app/__init__.py
niceterminal/app/controller.py
niceterminal/app/interfaces.py
niceterminal/app/ui.py
niceterminal/cli/__init__.py
niceterminal/errors.py
niceterminal/interface/__init__.py
niceterminal/interface/base.py
niceterminal/interface/persistant.py
niceterminal/interface/subprocess/__init__.py
niceterminal/interface/subprocess/posix.py
niceterminal/interface/subprocess/windows.py
niceterminal/lib/xterm.js/xterm.js
niceterminal/niceterminal.code-workspace
niceterminal/utils/__init__.py
niceterminal/xterm.js
niceterminal/xterm.py
niceterminal-0.1.2.dist-info/RECORD
