Metadata-Version: 2.1
Name: niceterminal
Version: 0.1.2
Summary: A library for building terminal applications with NiceGUI and rich terminal features.
Author-Email: Aki Mimoto <aki@bako.ca>
License: MIT-0
Project-URL: Homepage, https://github.com/amimoto/niceterminal
Project-URL: Issues, https://github.com/amimoto/niceterminal/issues
Requires-Python: >=3.9
Requires-Dist: nicegui>=2.5.0
Requires-Dist: pyte>=0.8.2
Requires-Dist: invoke>=2.1.3
Requires-Dist: pywinpty>=2.0.4; platform_system == "Windows"
Requires-Dist: loguru>=0.7.2
Requires-Dist: rich>=13.9.4
Provides-Extra: cli
Requires-Dist: docopt-ng>=0.9.0; extra == "cli"
